[
  {
    "name": "Kathmandu Heritage Core",
    "province": "Bagmati",
    "type": "Heritage City",
    "interests": ["Culture", "Food", "Family"],
    "bestSeasons": ["Spring", "Autumn", "Winter"],
    "budget": "Mid",
    "durationDays": 3,
    "summary": "Spend the day between old squares, shrine courtyards, and neighborhood eateries where Newari food is the real highlight.",
    "highlights": ["Pashupatinath evening aarti", "Boudhanath kora walk", "Patan backstreets"],
    "transport": "Easy road and flight access via Kathmandu",
    "budgetRange": "NPR 4,000-8,000 per day",
    "image": "../assets/images/bhaktapur.jpg",
    "provincePage": "../provinces/province3.html"
  },
  {
    "name": "Pokhara Lakeside Escape",
    "province": "Gandaki",
    "type": "Nature + City",
    "interests": ["Family", "Food", "Culture"],
    "bestSeasons": ["Spring", "Autumn", "Winter"],
    "budget": "Mid",
    "durationDays": 3,
    "summary": "Base yourself by the lake, catch sunrise over the Annapurnas, and keep days flexible for short hikes or cafe time.",
    "highlights": ["Phewa boat ride", "Sarangkot sunrise", "Peace Pagoda ridge"],
    "transport": "Tourist bus or 25-minute flight from Kathmandu",
    "budgetRange": "NPR 4,500-9,000 per day",
    "image": "../assets/images/phewa-lake.jpg",
    "provincePage": "../provinces/province4.html"
  },
  {
    "name": "Everest Gateway (Namche Route)",
    "province": "Koshi",
    "type": "High Mountain Trek",
    "interests": ["Trekking", "Spiritual"],
    "bestSeasons": ["Spring", "Autumn"],
    "budget": "High",
    "durationDays": 10,
    "summary": "A classic high-mountain route where trail tea houses, Sherpa villages, and big valley views shape each day.",
    "highlights": ["Lukla approach flight", "Namche acclimatization day", "Tengboche monastery stop"],
    "transport": "Flight to Lukla followed by multi-day trek",
    "budgetRange": "NPR 8,000-18,000 per day",
    "image": "../assets/images/namche.jpg",
    "provincePage": "../provinces/province1.html"
  },
  {
    "name": "Janakpur Pilgrimage Trail",
    "province": "Madhesh",
    "type": "Spiritual Circuit",
    "interests": ["Spiritual", "Culture", "Family"],
    "bestSeasons": ["Autumn", "Winter", "Spring"],
    "budget": "Low",
    "durationDays": 2,
    "summary": "Great for a short cultural break with temple visits, Mithila murals, and lively market streets around Janakpur.",
    "highlights": ["Janaki Mandir complex", "Mithila art workshops", "Janakpur old bazaar"],
    "transport": "Road and rail-linked from the Terai belt",
    "budgetRange": "NPR 2,500-5,000 per day",
    "image": "../assets/images/janaki-temple.jpg",
    "provincePage": "../provinces/province2.html"
  },
  {
    "name": "Lumbini Peace Journey",
    "province": "Lumbini",
    "type": "Spiritual Heritage",
    "interests": ["Spiritual", "Culture", "Family"],
    "bestSeasons": ["Winter", "Spring", "Autumn"],
    "budget": "Low",
    "durationDays": 2,
    "summary": "A calm, reflective route where monastery architecture and quiet walking paths make the pace naturally slow.",
    "highlights": ["Maya Devi sacred marker", "International monasteries", "Sunset in the Sacred Garden"],
    "transport": "Road from Bhairahawa airport hub",
    "budgetRange": "NPR 3,000-6,000 per day",
    "image": "../assets/images/lumbini.jpg",
    "provincePage": "../provinces/province5.html"
  },
  {
    "name": "Chitwan Wildlife Safari",
    "province": "Bagmati",
    "type": "Wildlife",
    "interests": ["Wildlife", "Family", "Food"],
    "bestSeasons": ["Winter", "Spring", "Autumn"],
    "budget": "Mid",
    "durationDays": 3,
    "summary": "Mix jungle drives with river-edge mornings and end the day with local Tharu food and dance programs.",
    "highlights": ["Rhino tracking drive", "Rapti canoe stretch", "Tharu community evening"],
    "transport": "Road transfer from Kathmandu or Pokhara",
    "budgetRange": "NPR 5,000-10,000 per day",
    "image": "../assets/images/chitwan.jpg",
    "provincePage": "../provinces/province3.html"
  },
  {
    "name": "Rara Lake Expedition",
    "province": "Karnali",
    "type": "Remote Nature",
    "interests": ["Trekking", "Wildlife"],
    "bestSeasons": ["Spring", "Autumn", "Summer"],
    "budget": "High",
    "durationDays": 7,
    "summary": "Remote and rewarding: clear lake water, long quiet trails, and a landscape that feels far from everything.",
    "highlights": ["Rara shoreline walk", "National park ridge points", "Early morning lake reflections"],
    "transport": "Domestic flight + jeep + short trek",
    "budgetRange": "NPR 7,500-15,000 per day",
    "image": "../assets/images/rara-lake.jpg",
    "provincePage": "../provinces/province6.html"
  },
  {
    "name": "Khaptad Highland Retreat",
    "province": "Sudurpashchim",
    "type": "Offbeat Nature",
    "interests": ["Trekking", "Spiritual", "Wildlife"],
    "bestSeasons": ["Spring", "Autumn", "Summer"],
    "budget": "Mid",
    "durationDays": 5,
    "summary": "An offbeat highland retreat with rolling meadows, pine forests, and simple trails between sacred sites.",
    "highlights": ["Khaptad meadow plateau", "Khaptad Baba Ashram trail", "Forest and grassland loop"],
    "transport": "Bus or flight to Dhangadhi then road + hike",
    "budgetRange": "NPR 4,500-9,500 per day",
    "image": "../assets/images/khaptad.jpg",
    "provincePage": "../provinces/province7.html"
  },
  {
    "name": "Ilam Tea Hills Weekend",
    "province": "Koshi",
    "type": "Scenic Retreat",
    "interests": ["Family", "Food", "Culture"],
    "bestSeasons": ["Spring", "Autumn", "Summer"],
    "budget": "Low",
    "durationDays": 3,
    "summary": "Ideal for a relaxed hill weekend with tea-garden walks, cool evenings, and broad sunrise viewpoints.",
    "highlights": ["Kanyam tea terraces", "Shree Antu sunrise", "Local tea tasting"],
    "transport": "Flight to Bhadrapur + road connection",
    "budgetRange": "NPR 3,500-6,500 per day",
    "image": "../assets/images/ilam-tea.jpg",
    "provincePage": "../provinces/province1.html"
  },
  {
    "name": "Bandipur Old Town Walk",
    "province": "Gandaki",
    "type": "Hill Heritage",
    "interests": ["Culture", "Food", "Family"],
    "bestSeasons": ["Spring", "Autumn", "Winter"],
    "budget": "Mid",
    "durationDays": 2,
    "summary": "A compact heritage stop where you can walk stone streets, watch mountain weather change, and slow down.",
    "highlights": ["Bandipur old bazaar", "Tundikhel open viewpoint", "Evening rooftop panorama"],
    "transport": "Road stop between Kathmandu and Pokhara",
    "budgetRange": "NPR 4,000-7,500 per day",
    "image": "../assets/images/bandipur-hill.jpg",
    "provincePage": "../provinces/province4.html"
  },
  {
    "name": "Upper Mustang Access Route",
    "province": "Gandaki",
    "type": "Desert Mountain Trek",
    "interests": ["Trekking", "Culture", "Spiritual"],
    "bestSeasons": ["Summer", "Spring", "Autumn"],
    "budget": "High",
    "durationDays": 9,
    "summary": "A dramatic dryland route with fortress towns, cliff monasteries, and open valleys unlike anywhere else in Nepal.",
    "highlights": ["Lo Manthang walls", "Sky-cave monastery visits", "Wind-carved Mustang valleys"],
    "transport": "Flight/road to Jomsom with restricted area permit",
    "budgetRange": "NPR 10,000-22,000 per day",
    "image": "../assets/images/lo-manthang.jpg",
    "provincePage": "../provinces/province4.html"
  },
  {
    "name": "Bardiya Wild Frontier",
    "province": "Lumbini",
    "type": "Wildlife",
    "interests": ["Wildlife", "Family"],
    "bestSeasons": ["Winter", "Spring"],
    "budget": "Mid",
    "durationDays": 4,
    "summary": "Quieter than the usual safari hubs, with good chances for long wildlife drives and serious birding.",
    "highlights": ["Bardiya tiger corridors", "Karnali river edge", "Wetland and grassland birding"],
    "transport": "Road/flight to Nepalgunj then transfer",
    "budgetRange": "NPR 5,500-11,000 per day",
    "image": "../assets/images/bardiya-national-park.jpg",
    "provincePage": "../provinces/province5.html"
  },
  {
    "name": "Shuklaphanta Wildlife Grasslands",
    "province": "Sudurpashchim",
    "type": "Wildlife",
    "interests": ["Wildlife", "Family", "Photography"],
    "bestSeasons": ["Winter", "Spring"],
    "budget": "Mid",
    "durationDays": 3,
    "summary": "Great for travelers who want open grasslands, fewer vehicles, and patient wildlife watching.",
    "highlights": ["Large swamp deer herds", "Shallow wetland zones", "Low-traffic tiger routes"],
    "transport": "Road from Dhangadhi and Mahendranagar",
    "budgetRange": "NPR 4,500-9,000 per day",
    "image": "../assets/images/shuklaphanta.jpg",
    "provincePage": "../provinces/province7.html"
  },
  {
    "name": "Pathibhara Temple Climb",
    "province": "Koshi",
    "type": "Pilgrimage Trek",
    "interests": ["Spiritual", "Trekking", "Culture"],
    "bestSeasons": ["Spring", "Autumn"],
    "budget": "Mid",
    "durationDays": 4,
    "summary": "A rewarding pilgrimage-style climb with wide ridgeline views, local tea stops, and a strong spiritual atmosphere.",
    "highlights": ["Pathibhara temple summit", "Cable car access segment", "Eastern Himalayan viewpoints"],
    "transport": "Road to Taplejung then trek/cable car",
    "budgetRange": "NPR 4,000-8,500 per day",
    "image": "../assets/images/pathibhara.jpg",
    "provincePage": "../provinces/province1.html"
  }
]
